ignition/__init__.py
ignition/__main__.py
ignition/exceptions.py
ignition/globals.py
ignition/request.py
ignition/response.py
ignition/url.py
ignition/util.py
ignition/python/__init__.py
ignition/python/python3_10/LICENSE_NOTICE
ignition/python/python3_10/__init__.py
ignition/python/python3_10/Lib/__init__.py
ignition/python/python3_10/Lib/urllib/__init__.py
ignition/python/python3_10/Lib/urllib/parse.py
ignition/python/python3_11/LICENSE_NOTICE
ignition/python/python3_11/__init__.py
ignition/python/python3_11/Lib/__init__.py
ignition/python/python3_11/Lib/urllib/__init__.py
ignition/python/python3_11/Lib/urllib/parse.py
ignition/python/python3_12/__init__.py
ignition/python/python3_12/Lib/__init__.py
ignition/python/python3_12/Lib/urllib/__init__.py
ignition/python/python3_12/Lib/urllib/parse.py
ignition/python/python3_7/LICENSE_NOTICE
ignition/python/python3_7/__init__.py
ignition/python/python3_7/Lib/__init__.py
ignition/python/python3_7/Lib/urllib/__init__.py
ignition/python/python3_7/Lib/urllib/parse.py
ignition/python/python3_8/LICENSE_NOTICE
ignition/python/python3_8/__init__.py
ignition/python/python3_8/Lib/__init__.py
ignition/python/python3_8/Lib/urllib/__init__.py
ignition/python/python3_8/Lib/urllib/parse.py
ignition/python/python3_9/LICENSE_NOTICE
ignition/python/python3_9/__init__.py
ignition/python/python3_9/Lib/__init__.py
ignition/python/python3_9/Lib/urllib/__init__.py
ignition/python/python3_9/Lib/urllib/parse.py
ignition/ssl/__init__.py
ignition/ssl/cert_record.py
ignition/ssl/cert_store.py
ignition/ssl/cert_wrapper.py
ignition_gemini-1.0.0.dist-info/METADATA
ignition_gemini-1.0.0.dist-info/WHEEL
ignition_gemini-1.0.0.dist-info/licenses/LICENSE
ignition_gemini-1.0.0.dist-info/RECORD
