Metadata-Version: 2.3
Name: ignition-gemini
Version: 1.0.0
Summary: ignition - Gemini Protocol Client Transport Library
Project-URL: Homepage, https://github.com/cbrews/ignition
Author-email: Chris Brousseau <cbrews@users.noreply.github.com>
License: MPL 2.0
License-File: LICENSE
Keywords: client,gemini,networking,request,socket
Classifier: Development Status :: 7 - Inactive
Classifier: Intended Audience :: Developers
Classifier: License :: OSI Approved :: Mozilla Public License 2.0 (MPL 2.0)
Classifier: Programming Language :: Python :: 3
Classifier: Programming Language :: Python :: 3 :: Only
Classifier: Programming Language :: Python :: 3.7
Classifier: Programming Language :: Python :: 3.8
Classifier: Programming Language :: Python :: 3.9
Classifier: Programming Language :: Python :: 3.10
Classifier: Programming Language :: Python :: 3.11
Classifier: Programming Language :: Python :: 3.12
Classifier: Topic :: Software Development :: Libraries
Requires-Python: >=3.7
Requires-Dist: cryptography>=36.0.0
Provides-Extra: build
Requires-Dist: build; extra == 'build'
Requires-Dist: twine; extra == 'build'
Provides-Extra: dev
Requires-Dist: black==24.4.0; extra == 'dev'
Requires-Dist: cryptography==42.0.5; extra == 'dev'
Requires-Dist: mock==5.1.0; extra == 'dev'
Requires-Dist: pre-commit==3.7.0; extra == 'dev'
Requires-Dist: pytest-cov==4.1.0; extra == 'dev'
Requires-Dist: pytest-mock==3.11.1; extra == 'dev'
Requires-Dist: pytest==7.4.4; extra == 'dev'
Requires-Dist: ruff==0.4.0; extra == 'dev'
Provides-Extra: lint
Requires-Dist: black==24.4.0; extra == 'lint'
Requires-Dist: mock==5.1.0; extra == 'lint'
Requires-Dist: pytest==7.4.4; extra == 'lint'
Requires-Dist: ruff==0.4.0; extra == 'lint'
Provides-Extra: test
Requires-Dist: mock==5.1.0; extra == 'test'
Requires-Dist: pytest-cov==4.1.0; extra == 'test'
Requires-Dist: pytest-mock==3.11.1; extra == 'test'
Requires-Dist: pytest==7.4.4; extra == 'test'
